arcor2_execution/VERSION
arcor2_execution/__init__.py
arcor2_execution/py.typed
arcor2_execution/scripts/__init__.py
arcor2_execution/scripts/execution.py
arcor2_execution-1.6.0.dist-info/METADATA
arcor2_execution-1.6.0.dist-info/WHEEL
arcor2_execution-1.6.0.dist-info/entry_points.txt
arcor2_execution-1.6.0.dist-info/namespace_packages.txt
arcor2_execution-1.6.0.dist-info/top_level.txt
arcor2_execution-1.6.0.dist-info/RECORD
