Metadata-Version: 2.1
Name: arcor2-execution
Version: 1.6.0
Summary: ARCOR2 Execution service
Author: Robo@FIT
Author-email: imaterna@fit.vut.cz
License: LGPL
Classifier: Development Status :: 3 - Alpha
Classifier: Intended Audience :: Developers
Classifier: Topic :: Software Development :: Build Tools
Classifier: License :: OSI Approved :: GNU Lesser General Public License v3 (LGPLv3)
Classifier: Programming Language :: Python :: 3.11
Classifier: Natural Language :: English
Classifier: Topic :: Scientific/Engineering
Requires-Python: ==3.11.*
Requires-Dist: aiofiles (~=23.2.1)
Requires-Dist: aiologger (~=0.7.0)
Requires-Dist: aiorun (~=2024.5.1)
Requires-Dist: arcor2-execution-data (~=1.2.0)
Requires-Dist: arcor2-runtime (~=1.4.0)
Requires-Dist: arcor2 (~=1.5.0)
Requires-Dist: dataclasses-jsonschema[apispec,fast-dateparsing,fast-validation] (~=2.16.0)
Requires-Dist: types-aiofiles (==23.2.0.20240403)
Requires-Dist: websockets (~=12.0)
